poetry_bundle_plugin/__init__.py
poetry_bundle_plugin/bundlers/__init__.py
poetry_bundle_plugin/bundlers/bundler.py
poetry_bundle_plugin/bundlers/bundler_manager.py
poetry_bundle_plugin/bundlers/venv_bundler.py
poetry_bundle_plugin/console/__init__.py
poetry_bundle_plugin/console/commands/__init__.py
poetry_bundle_plugin/console/commands/bundle/__init__.py
poetry_bundle_plugin/console/commands/bundle/bundle_command.py
poetry_bundle_plugin/console/commands/bundle/venv.py
poetry_bundle_plugin/exceptions.py
poetry_bundle_plugin/plugin.py
poetry_bundle_plugin-0.1.0.dist-info/entry_points.txt
poetry_bundle_plugin-0.1.0.dist-info/WHEEL
poetry_bundle_plugin-0.1.0.dist-info/METADATA
poetry_bundle_plugin-0.1.0.dist-info/RECORD
